LICENSE
MANIFEST.in
README.md
setup.cfg
setup.py
bpptkg_querybulletin.egg-info/PKG-INFO
bpptkg_querybulletin.egg-info/SOURCES.txt
bpptkg_querybulletin.egg-info/dependency_links.txt
bpptkg_querybulletin.egg-info/entry_points.txt
bpptkg_querybulletin.egg-info/requires.txt
bpptkg_querybulletin.egg-info/top_level.txt
bpptkg_querybulletin.egg-info/zip-safe
querybulletin/__init__.py
querybulletin/__main__.py
querybulletin/cli.py
querybulletin/exceptions.py
querybulletin/models.py
querybulletin/query.py
querybulletin/sessions.py
querybulletin/settings.py
querybulletin/utils.py
querybulletin/version.py