Metadata-Version: 2.1
Name: bpptkg-querybulletin
Version: 0.3.0
Summary: Simple Python library to query seismic bulletin database
Home-page: https://github.com/bpptkg/bpptkg-querybulletin
Author: BPPTKG
Author-email: bpptkg@esdm.go.id
License: MIT
Platform: UNKNOWN
Classifier: Development Status :: 5 - Production/Stable
Classifier: Environment :: Console
Classifier: Operating System :: OS Independent
Classifier: Intended Audience :: Science/Research
Classifier: License :: OSI Approved :: MIT License
Classifier: Natural Language :: English
Classifier: Programming Language :: Python :: 2
Classifier: Programming Language :: Python :: 2.7
Classifier: Programming Language :: Python :: 3
Classifier: Programming Language :: Python :: 3.6
Classifier: Programming Language :: Python :: 3.7
Classifier: Programming Language :: Python :: 3.8
Classifier: Programming Language :: Python :: 3.9
